axclh/main.py
axclh-0.0.4.dist-info/METADATA
axclh-0.0.4.dist-info/WHEEL
axclh-0.0.4.dist-info/entry_points.txt
axclh-0.0.4.dist-info/top_level.txt
axclh-0.0.4.dist-info/RECORD
