Metadata-Version: 2.1
Name: axclh
Version: 0.0.4
Summary: Package that helps find quick answers realy quick
Home-page: UNKNOWN
Author: axdjuraev
License: UNKNOWN
Platform: UNKNOWN
Requires-Dist: click (==8.1.3)
Requires-Dist: inquirer (==3.1.3)
Requires-Dist: requests
